nosp/__init__.py
nosp/_internal.py
nosp/cache.py
nosp/config.py
nosp/core.py
nosp/database.py
nosp/err.py
nosp/file.py
nosp/http.py
nosp/lazy.py
nosp/monitor.py
nosp/mq.py
nosp/parse.py
nosp/spider.py
nosp/utils.py
nosp-0.8.7.dist-info/METADATA
nosp-0.8.7.dist-info/WHEEL
nosp-0.8.7.dist-info/top_level.txt
nosp-0.8.7.dist-info/RECORD
