Metadata-Version: 2.4
Name: nosp
Version: 0.8.7
Author-email: noybzy <noybzy@qq.com>
Requires-Python: >=3.9
Requires-Dist: dbutils==3.1.0
Requires-Dist: loguru>=0.7.3
Requires-Dist: parsel==1.10.0
Requires-Dist: pymysql==1.1.1
Requires-Dist: requests>=2.32.3
